cvr/__init__.py
cvr/client.py
cvr/cvr_client.py
cvr/errors.py
cvr/http_helpers.py
cvr/dto/__init__.py
cvr/dto/produktionsenhed.py
cvr/dto/utils.py
cvr/dto/virksomhed.py
cvr-0.2.2.dist-info/LICENSE
cvr-0.2.2.dist-info/METADATA
cvr-0.2.2.dist-info/WHEEL
cvr-0.2.2.dist-info/top_level.txt
cvr-0.2.2.dist-info/RECORD
