Metadata-Version: 2.1
Name: cvr
Version: 0.2.2
Summary: Official Python client for https://cvr.dev
Home-page: https://github.com/cvr-dev/cvr.dev-python
Author: cvr.dev
Author-email: kontakt@cvr.dev
License: UNKNOWN
Platform: UNKNOWN
Classifier: Programming Language :: Python :: 3
Classifier: License :: OSI Approved :: MIT License
Classifier: Intended Audience :: Developers
Classifier: Operating System :: OS Independent
Classifier: License :: OSI Approved :: Apache Software License
Classifier: Topic :: Software Development
Requires-Python: >=3.5
